Data.py
Gates.py
Graph.py
NoisyEvolution.py
Operations.py
QCircuit.py
SpecialStates.py
qubit_class.py
qComputing/Data.py
qComputing/Gates.py
qComputing/Graph.py
qComputing/NoisyEvolution.py
qComputing/Operations.py
qComputing/QCircuit.py
qComputing/SpecialStates.py
qComputing/__init__.py
qComputing/qubit_class.py
qComputing-1.8.3.dist-info/METADATA
qComputing-1.8.3.dist-info/RECORD
qComputing-1.8.3.dist-info/WHEEL
qComputing-1.8.3.dist-info/top_level.txt
