Metadata-Version: 2.1
Name: qComputing
Version: 1.8.3
Summary: A package which deals with light weight routine quantum computing stuff
Home-page: https://github.com/akataba/qComputing
Author: Amara Katabarwa
Author-email: Henriamaa@gmail.com
License: UNKNOWN
Platform: UNKNOWN
Classifier: Programming Language :: Python :: 3
Classifier: License :: OSI Approved :: MIT License
Classifier: Operating System :: OS Independent
